setup.py
django_portfolio.egg-info/PKG-INFO
django_portfolio.egg-info/SOURCES.txt
django_portfolio.egg-info/dependency_links.txt
django_portfolio.egg-info/requires.txt
django_portfolio.egg-info/top_level.txt
portfolio/__init__.py
portfolio/blog/__init__.py
portfolio/blog/models.py
portfolio/contact/__init__.py
portfolio/contact/forms.py
portfolio/contact/models.py
portfolio/projects/__init__.py
portfolio/projects/models.py
portfolio/utils/__init__.py
portfolio/utils/models.py