Metadata-Version: 1.0
Name: django-portfolio
Version: 0.0.5-pre-alpha
Summary: A simple set of abstract models and functionality to speed up the development of a portfolio type site in Django 1.3+
Home-page: https://igniteflow@github.com/igniteflow/django-portfolio.git
Author: Phil Tysoe
Author-email: philtysoe@gmail.com
License: BSD
Keywords: Django,portfolio,blog,artist
Platform: linux
Classifier: Environment :: Web Environment
Classifier: Framework :: Django
Classifier: Intended Audience :: Developers
Classifier: License :: OSI Approved :: BSD License
Classifier: Operating System :: Unix
Classifier: Programming Language :: Python
